imfont/.version
imfont/__init__.py
imfont/font2c
imfont/imfont.py
imfont/main.py
imfont-0.0.5.dist-info/LICENSE
imfont-0.0.5.dist-info/METADATA
imfont-0.0.5.dist-info/WHEEL
imfont-0.0.5.dist-info/entry_points.txt
imfont-0.0.5.dist-info/top_level.txt
imfont-0.0.5.dist-info/RECORD
