Metadata-Version: 2.1
Name: imfont
Version: 0.0.5
Summary: Imfont: a versatile Python tool for converting fonts and images into C++ arrays. Generate compact code for embedded systems or ImGui applications with rich console features. Simplify graphic resource integration. Created by HK4CRPRASAD. #Python #EmbeddedSystems #Imfont
Home-page: https://github.com/hk4crprasad/imfont
Download-URL: https://github.com/hk4crprasad/imfont/archive/pypi.zip
Author: HK4CRPRASAD
Author-email: hotahara12@gmail.com
License: GPL-3.0
Keywords: font,img,cpp
Classifier: Development Status :: 4 - Beta
Classifier: Intended Audience :: Developers
Classifier: Topic :: Software Development :: Libraries :: Python Modules
Classifier: License :: OSI Approved :: GNU General Public License v3 (GPLv3)
Classifier: Programming Language :: Python :: 3
Classifier: Programming Language :: Python :: 3.6
Classifier: Programming Language :: Python :: 3.7
Classifier: Programming Language :: Python :: 3.8
Classifier: Programming Language :: Python :: 3.9
Classifier: Programming Language :: Python :: 3.10
Classifier: Programming Language :: Python :: 3.11
Classifier: Operating System :: OS Independent
Classifier: Topic :: Communications :: Chat
Requires-Python: >=3.6
License-File: LICENSE
Requires-Dist: rich
Requires-Dist: setuptools
Requires-Dist: requests
